blendlib.cpython-38-darwin.so
library/__init__.py
library/blendlib.c
library/blendlib.so
library/library.py
library/main.py
library/wsl.py
photoblend-1.2.2.data/data/blendlib.so
photoblend-1.2.2.data/data/blue.jpg
photoblend-1.2.2.data/data/colorful.png
photoblend-1.2.2.data/data/desert.jpg
photoblend-1.2.2.data/data/fractal2.jpg
photoblend-1.2.2.data/data/icon.png
photoblend-1.2.2.data/data/red.jpg
photoblend-1.2.2.data/data/ring.png
photoblend-1.2.2.data/data/white.jpg
photoblend-1.2.2.dist-info/LICENSE
photoblend-1.2.2.dist-info/METADATA
photoblend-1.2.2.dist-info/WHEEL
photoblend-1.2.2.dist-info/entry_points.txt
photoblend-1.2.2.dist-info/top_level.txt
photoblend-1.2.2.dist-info/RECORD
